cascade/__init__.py
cascade/core.py
cascade/data.py
cascade/graph.py
cascade/main.py
cascade/metrics.py
cascade/model.py
cascade/nn.py
cascade/plot.py
cascade/ri.py
cascade/sim.py
cascade/typing.py
cascade/utils.py
cascade_reg-0.5.1.dist-info/entry_points.txt
cascade_reg-0.5.1.dist-info/licenses/LICENSE
cascade_reg-0.5.1.dist-info/WHEEL
cascade_reg-0.5.1.dist-info/METADATA
cascade_reg-0.5.1.dist-info/RECORD
