Metadata-Version: 2.4
Name: cascade-reg
Version: 0.5.1
Summary: Causal discovery of gene regulatory programs from single-cell genomics
Keywords: bioinformatics,causal-discovery,causal-inference,deep-learning,gene-regulatory-network,single-cell
Author-email: Zhi-Jie Cao <caozj@mail.cbi.pku.edu.cn>
Requires-Python: >=3.8
Classifier: Intended Audience :: Science/Research
Classifier: License :: OSI Approved :: MIT License
Classifier: Natural Language :: English
Classifier: Operating System :: MacOS :: MacOS X
Classifier: Operating System :: POSIX :: Linux
Classifier: Programming Language :: Python :: 3
Classifier: Programming Language :: Python :: 3.8
Classifier: Programming Language :: Python :: 3.9
Classifier: Programming Language :: Python :: 3.10
Classifier: Programming Language :: Python :: 3.11
Classifier: Topic :: Scientific/Engineering :: Bio-Informatics
License-File: LICENSE
Requires-Dist: anndata
Requires-Dist: adjustText
Requires-Dist: kneed
Requires-Dist: loguru
Requires-Dist: matplotlib
Requires-Dist: networkx
Requires-Dist: numpy
Requires-Dist: pandas
Requires-Dist: pynvml
Requires-Dist: pytorch-lightning>=2
Requires-Dist: pyyaml
Requires-Dist: rich
Requires-Dist: scanpy
Requires-Dist: scikit-learn
Requires-Dist: scipy
Requires-Dist: seaborn
Requires-Dist: tensorboard
Requires-Dist: torch>=2
Requires-Dist: sphinx ; extra == "doc"
Requires-Dist: sphinx-autobuild ; extra == "doc"
Requires-Dist: sphinx-autodoc-typehints ; extra == "doc"
Requires-Dist: sphinx-rtd-theme ; extra == "doc"
Requires-Dist: sphinx-copybutton ; extra == "doc"
Requires-Dist: sphinxcontrib-programoutput ; extra == "doc"
Requires-Dist: nbsphinx ; extra == "doc"
Requires-Dist: allpairspy ; extra == "test"
Requires-Dist: black<25 ; extra == "test"
Requires-Dist: dynamicTreeCut ; extra == "test"
Requires-Dist: filelock ; extra == "test"
Requires-Dist: flake8 ; extra == "test"
Requires-Dist: opencv-python ; extra == "test"
Requires-Dist: plotly ; extra == "test"
Requires-Dist: pytest-cov ; extra == "test"
Requires-Dist: pytest ; extra == "test"
Project-URL: Github, https://github.com/gao-lab/CASCADE-dev
Provides-Extra: doc
Provides-Extra: test
